[{"x": 13263.0, "z": -6208.1, "width": 9.1, "depth": 14.3, "floors": 1, "type": "yes", "name": ""}, {"x": 13231.8, "z": -6556.2, "width": 4.4, "depth": 7.7, "floors": 1, "type": "yes", "name": ""}, {"x": 12626.1, "z": -6125.3, "width": 9.9, "depth": 5.3, "floors": 1, "type": "yes", "name": ""}, {"x": 13269.6, "z": -7016.2, "width": 4.9, "depth": 22.7, "floors": 1, "type": "yes", "name": ""}, {"x": 12004.8, "z": -7827.5, "width": 4, "depth": 10.9, "floors": 1, "type": "yes", "name": ""}, {"x": 13201.8, "z": -6191.9, "width": 4, "depth": 14.3, "floors": 1, "type": "yes", "name": ""}, {"x": 13179.6, "z": -6369.1, "width": 4, "depth": 6.3, "floors": 1, "type": "yes", "name": ""}, {"x": 13522.9, "z": -6101.9, "width": 8.2, "depth": 7.0, "floors": 1, "type": "yes", "name": ""}, {"x": 13499.3, "z": -6198.6, "width": 7.2, "depth": 5.6, "floors": 1, "type": "yes", "name": ""}, {"x": 12018.0, "z": -7741.6, "width": 25.1, "depth": 38.5, "floors": 1, "type": "yes", "name": ""}, {"x": 12020.5, "z": -7895.2, "width": 4, "depth": 8.8, "floors": 1, "type": "yes", "name": ""}, {"x": 13482.4, "z": -7495.3, "width": 4, "depth": 4.6, "floors": 1, "type": "yes", "name": ""}, {"x": 12652.4, "z": -7899.9, "width": 11.7, "depth": 11.8, "floors": 1, "type": "yes", "name": ""}, {"x": 12057.2, "z": -7695.4, "width": 5.0, "depth": 30.6, "floors": 1, "type": "yes", "name": ""}, {"x": 12631.7, "z": -7906.1, "width": 6.8, "depth": 17.6, "floors": 1, "type": "yes", "name": ""}, {"x": 12004.5, "z": -7851.6, "width": 9.7, "depth": 5.8, "floors": 1, "type": "yes", "name": ""}, {"x": 13527.6, "z": -6077.8, "width": 4, "depth": 11.0, "floors": 1, "type": "yes", "name": ""}, {"x": 12024.5, "z": -7791.2, "width": 6.0, "depth": 8.8, "floors": 1, "type": "yes", "name": ""}, {"x": 12657.8, "z": -6136.7, "width": 4.5, "depth": 8.3, "floors": 1, "type": "yes", "name": ""}, {"x": 13488.2, "z": -7519.5, "width": 4, "depth": 4.1, "floors": 1, "type": "yes", "name": ""}, {"x": 12632.9, "z": -6151.7, "width": 4.3, "depth": 15.6, "floors": 1, "type": "yes", "name": ""}, {"x": 12017.3, "z": -7862.5, "width": 12.5, "depth": 20.7, "floors": 1, "type": "yes", "name": ""}, {"x": 13231.2, "z": -7163.1, "width": 18.8, "depth": 19.5, "floors": 1, "type": "yes", "name": ""}, {"x": 13192.0, "z": -7985.9, "width": 5.3, "depth": 8.1, "floors": 1, "type": "yes", "name": ""}, {"x": 13196.6, "z": -6371.6, "width": 4.2, "depth": 12.5, "floors": 1, "type": "yes", "name": ""}, {"x": 13519.4, "z": -6065.3, "width": 5.8, "depth": 13.4, "floors": 1, "type": "yes", "name": ""}, {"x": 12653.1, "z": -6130.1, "width": 4, "depth": 5.9, "floors": 1, "type": "yes", "name": ""}, {"x": 13540.2, "z": -6412.9, "width": 4, "depth": 4.3, "floors": 1, "type": "yes", "name": ""}, {"x": 13218.8, "z": -7058.5, "width": 4.1, "depth": 12.5, "floors": 1, "type": "yes", "name": ""}, {"x": 13550.5, "z": -6306.8, "width": 8.5, "depth": 10.0, "floors": 1, "type": "yes", "name": ""}, {"x": 13479.3, "z": -7512.1, "width": 4.7, "depth": 6.6, "floors": 1, "type": "yes", "name": ""}, {"x": 12667.0, "z": -6178.5, "width": 5.3, "depth": 9.5, "floors": 1, "type": "yes", "name": ""}, {"x": 12671.4, "z": -6175.5, "width": 7.3, "depth": 11.3, "floors": 1, "type": "yes", "name": ""}, {"x": 13215.5, "z": -7183.0, "width": 5.8, "depth": 10.8, "floors": 1, "type": "yes", "name": ""}, {"x": 13250.1, "z": -6608.6, "width": 9.3, "depth": 14.4, "floors": 1, "type": "yes", "name": ""}, {"x": 13229.5, "z": -7190.9, "width": 9.6, "depth": 13.5, "floors": 1, "type": "yes", "name": ""}, {"x": 12026.2, "z": -7843.0, "width": 12.3, "depth": 14.6, "floors": 1, "type": "yes", "name": ""}, {"x": 13208.1, "z": -7173.5, "width": 4, "depth": 4.3, "floors": 1, "type": "yes", "name": ""}, {"x": 12045.0, "z": -7685.4, "width": 4, "depth": 16.4, "floors": 1, "type": "yes", "name": ""}, {"x": 12024.2, "z": -7717.8, "width": 7.4, "depth": 7.6, "floors": 1, "type": "yes", "name": ""}, {"x": 13173.9, "z": -7957.6, "width": 12.8, "depth": 6.5, "floors": 1, "type": "yes", "name": ""}, {"x": 13231.6, "z": -7179.8, "width": 13.8, "depth": 9.4, "floors": 1, "type": "yes", "name": ""}, {"x": 13493.5, "z": -7516.5, "width": 4, "depth": 10.0, "floors": 1, "type": "yes", "name": ""}, {"x": 13379.3, "z": -7155.3, "width": 7.6, "depth": 19.7, "floors": 1, "type": "yes", "name": ""}, {"x": 13496.6, "z": -6208.0, "width": 4, "depth": 6.2, "floors": 1, "type": "yes", "name": ""}, {"x": 12023.3, "z": -7780.1, "width": 4, "depth": 4, "floors": 1, "type": "yes", "name": ""}, {"x": 13190.3, "z": -7956.7, "width": 9.0, "depth": 25.4, "floors": 1, "type": "yes", "name": ""}, {"x": 13540.0, "z": -6381.4, "width": 8.6, "depth": 18.0, "floors": 1, "type": "yes", "name": ""}, {"x": 13480.6, "z": -6196.5, "width": 4.4, "depth": 38.3, "floors": 1, "type": "yes", "name": ""}, {"x": 12007.3, "z": -7768.7, "width": 9.8, "depth": 7.3, "floors": 1, "type": "yes", "name": ""}, {"x": 13200.9, "z": -6350.9, "width": 4, "depth": 4, "floors": 1, "type": "yes", "name": ""}, {"x": 13181.7, "z": -7974.6, "width": 5.8, "depth": 20.0, "floors": 1, "type": "yes", "name": ""}, {"x": 13500.9, "z": -6257.0, "width": 6.3, "depth": 14.4, "floors": 1, "type": "yes", "name": ""}, {"x": 13544.3, "z": -6266.3, "width": 6.8, "depth": 6.7, "floors": 1, "type": "yes", "name": ""}, {"x": 13238.7, "z": -6513.7, "width": 4.5, "depth": 12.6, "floors": 1, "type": "yes", "name": ""}, {"x": 13190.9, "z": -6356.2, "width": 4.2, "depth": 13.2, "floors": 1, "type": "yes", "name": ""}, {"x": 13229.4, "z": -7048.4, "width": 4, "depth": 4.4, "floors": 1, "type": "yes", "name": ""}, {"x": 12003.9, "z": -7796.8, "width": 9.7, "depth": 26.6, "floors": 1, "type": "yes", "name": ""}, {"x": 13225.8, "z": -7226.4, "width": 7.7, "depth": 11.2, "floors": 1, "type": "yes", "name": ""}, {"x": 12589.2, "z": -6306.4, "width": 9.4, "depth": 9.9, "floors": 1, "type": "house", "name": ""}, {"x": 13925.3, "z": -6692.1, "width": 13.2, "depth": 21.4, "floors": 1, "type": "yes", "name": ""}, {"x": 13939.8, "z": -6706.0, "width": 20.4, "depth": 28.7, "floors": 1, "type": "yes", "name": ""}, {"x": 13880.6, "z": -6643.9, "width": 4.1, "depth": 7.1, "floors": 1, "type": "yes", "name": ""}, {"x": 13889.9, "z": -6644.7, "width": 6.4, "depth": 13.9, "floors": 1, "type": "house", "name": ""}, {"x": 13766.3, "z": -6510.9, "width": 4, "depth": 4, "floors": 1, "type": "yes", "name": ""}, {"x": 13762.8, "z": -6494.8, "width": 5.9, "depth": 11.2, "floors": 1, "type": "yes", "name": ""}, {"x": 13770.0, "z": -6498.5, "width": 7.9, "depth": 11.3, "floors": 1, "type": "house", "name": ""}, {"x": 13249.6, "z": -6220.4, "width": 11.1, "depth": 17.9, "floors": 1, "type": "yes", "name": ""}, {"x": 13596.7, "z": -6406.9, "width": 4.8, "depth": 20.5, "floors": 1, "type": "yes", "name": ""}, {"x": 13596.8, "z": -6343.9, "width": 10.2, "depth": 13.2, "floors": 1, "type": "yes", "name": ""}, {"x": 13183.2, "z": -7755.3, "width": 5.7, "depth": 13.6, "floors": 1, "type": "house", "name": ""}, {"x": 13219.8, "z": -7887.4, "width": 4.2, "depth": 13.8, "floors": 1, "type": "house", "name": ""}, {"x": 12037.6, "z": -7209.0, "width": 4.1, "depth": 18.0, "floors": 1, "type": "yes", "name": ""}, {"x": 12095.6, "z": -6049.6, "width": 4.4, "depth": 10.9, "floors": 1, "type": "house", "name": ""}, {"x": 13417.6, "z": -7912.5, "width": 6.1, "depth": 9.4, "floors": 1, "type": "yes", "name": ""}, {"x": 12104.4, "z": -6074.9, "width": 7.8, "depth": 8.5, "floors": 1, "type": "yes", "name": ""}, {"x": 12098.4, "z": -6061.7, "width": 5.4, "depth": 4.1, "floors": 1, "type": "yes", "name": ""}, {"x": 12112.8, "z": -6047.4, "width": 10.5, "depth": 8.5, "floors": 1, "type": "yes", "name": ""}, {"x": 13410.1, "z": -7902.3, "width": 4, "depth": 4, "floors": 1, "type": "yes", "name": ""}, {"x": 12106.4, "z": -6032.9, "width": 4, "depth": 9.0, "floors": 1, "type": "yes", "name": ""}]