[{"coords": [{"x": -8330.3, "z": 14000.1}, {"x": -8330.8, "z": 14003.3}, {"x": -8331.5, "z": 14005.5}, {"x": -8336.6, "z": 14015.9}, {"x": -8340.8, "z": 14025.2}, {"x": -8345.0, "z": 14033.2}, {"x": -8346.0, "z": 14034.6}, {"x": -8347.4, "z": 14035.4}, {"x": -8350.6, "z": 14036.3}, {"x": -8355.2, "z": 14036.9}, {"x": -8366.1, "z": 14037.6}, {"x": -8368.0, "z": 14037.6}, {"x": -8378.6, "z": 14038.6}, {"x": -8384.5, "z": 14037.5}], "type": "residential", "name": ""}, {"coords": [{"x": -8290.8, "z": 14101.8}, {"x": -8293.4, "z": 14102.9}, {"x": -8294.7, "z": 14102.6}, {"x": -8295.9, "z": 14101.0}, {"x": -8307.4, "z": 14048.0}, {"x": -8311.8, "z": 14025.6}, {"x": -8313.1, "z": 14019.8}, {"x": -8314.4, "z": 14016.2}, {"x": -8315.6, "z": 14013.7}, {"x": -8317.0, "z": 14011.4}, {"x": -8321.1, "z": 14006.9}, {"x": -8324.6, "z": 14004.0}, {"x": -8330.3, "z": 14000.1}, {"x": -8337.7, "z": 13997.7}, {"x": -8343.3, "z": 13997.1}, {"x": -8387.8, "z": 13997.5}, {"x": -8407.4, "z": 13996.7}], "type": "service", "name": ""}, {"coords": [{"x": -8334.2, "z": 14097.1}, {"x": -8336.6, "z": 14083.5}, {"x": -8340.9, "z": 14062.7}, {"x": -8347.4, "z": 14035.4}], "type": "service", "name": ""}, {"coords": [{"x": -9003.7, "z": 15534.1}, {"x": -8961.5, "z": 15391.1}], "type": "service", "name": ""}, {"coords": [{"x": -8307.4, "z": 14048.0}, {"x": -8302.7, "z": 14045.2}], "type": "service", "name": ""}, {"coords": [{"x": -8877.3, "z": 14496.0}, {"x": -8876.8, "z": 14479.0}, {"x": -8873.5, "z": 14410.6}, {"x": -8872.8, "z": 14321.7}, {"x": -8874.6, "z": 14223.0}, {"x": -8874.5, "z": 14196.1}, {"x": -8870.9, "z": 14176.4}, {"x": -8865.7, "z": 14165.8}, {"x": -8835.7, "z": 14114.4}, {"x": -8832.2, "z": 14106.9}, {"x": -8829.0, "z": 14095.2}], "type": "service", "name": ""}, {"coords": [{"x": -8804.9, "z": 15526.3}, {"x": -8722.7, "z": 15344.8}, {"x": -8717.9, "z": 15330.7}, {"x": -8715.1, "z": 15309.0}, {"x": -8714.6, "z": 15274.6}, {"x": -8710.4, "z": 15260.4}], "type": "service", "name": ""}, {"coords": [{"x": -9598.5, "z": 15928.3}, {"x": -9599.4, "z": 15778.8}, {"x": -9599.4, "z": 15740.6}, {"x": -9599.9, "z": 15584.0}, {"x": -9600.3, "z": 15575.7}, {"x": -9600.7, "z": 15572.4}, {"x": -9601.9, "z": 15566.4}, {"x": -9603.8, "z": 15559.4}, {"x": -9604.9, "z": 15556.5}, {"x": -9608.9, "z": 15548.8}, {"x": -9614.9, "z": 15540.0}, {"x": -9624.1, "z": 15528.9}, {"x": -9637.9, "z": 15511.8}, {"x": -9714.8, "z": 15416.6}, {"x": -9740.0, "z": 15385.5}, {"x": -9745.4, "z": 15377.9}, {"x": -9748.2, "z": 15373.3}, {"x": -9750.5, "z": 15368.5}, {"x": -9751.5, "z": 15366.4}, {"x": -9753.6, "z": 15361.0}, {"x": -9755.3, "z": 15353.8}, {"x": -9756.8, "z": 15343.4}, {"x": -9757.0, "z": 15340.7}, {"x": -9757.0, "z": 15314.0}, {"x": -9757.0, "z": 15240.9}, {"x": -9757.2, "z": 15184.5}, {"x": -9757.2, "z": 15131.0}, {"x": -9756.5, "z": 15079.7}, {"x": -9756.3, "z": 15043.5}, {"x": -9756.7, "z": 15039.9}, {"x": -9758.4, "z": 15036.0}], "type": "residential", "name": "Robin Road"}, {"coords": [{"x": -8385.5, "z": 15991.0}, {"x": -8354.3, "z": 15923.8}, {"x": -8324.5, "z": 15860.4}, {"x": -8310.0, "z": 15828.4}, {"x": -8300.5, "z": 15805.7}, {"x": -8297.3, "z": 15797.2}, {"x": -8285.8, "z": 15764.3}, {"x": -8277.4, "z": 15739.0}, {"x": -8275.5, "z": 15731.8}, {"x": -8274.5, "z": 15727.6}, {"x": -8273.6, "z": 15722.2}, {"x": -8273.0, "z": 15716.7}, {"x": -8272.6, "z": 15710.4}, {"x": -8272.4, "z": 15706.9}, {"x": -8272.3, "z": 15703.7}, {"x": -8272.3, "z": 15541.1}, {"x": -8272.5, "z": 15503.9}, {"x": -8273.8, "z": 15183.3}, {"x": -8273.8, "z": 15110.7}, {"x": -8274.2, "z": 15038.3}, {"x": -8274.6, "z": 15002.4}, {"x": -8275.0, "z": 14894.3}, {"x": -8274.9, "z": 14775.6}, {"x": -8275.3, "z": 14638.6}, {"x": -8275.3, "z": 14593.3}, {"x": -8275.2, "z": 14492.7}, {"x": -8275.6, "z": 14347.0}, {"x": -8275.5, "z": 14224.8}, {"x": -8275.6, "z": 14204.6}, {"x": -8275.4, "z": 14178.8}, {"x": -8275.3, "z": 14175.9}, {"x": -8275.0, "z": 14173.1}, {"x": -8274.5, "z": 14170.9}], "type": "residential", "name": "Forest Road"}, {"coords": [{"x": -9232.6, "z": 15271.2}, {"x": -9186.4, "z": 15273.0}, {"x": -9171.2, "z": 15271.7}, {"x": -9167.7, "z": 15271.2}, {"x": -9163.1, "z": 15270.1}, {"x": -9153.9, "z": 15267.3}, {"x": -9023.8, "z": 15219.0}, {"x": -9020.7, "z": 15218.2}, {"x": -9015.0, "z": 15217.9}], "type": "residential", "name": "West Owl Road"}, {"coords": [{"x": -9014.5, "z": 14996.5}, {"x": -9041.3, "z": 14997.6}, {"x": -9051.9, "z": 14997.7}, {"x": -9076.1, "z": 14996.2}, {"x": -9082.2, "z": 14996.8}], "type": "residential", "name": "Walter Road"}, {"coords": [{"x": -9285.5, "z": 15991.8}, {"x": -9277.8, "z": 15977.6}, {"x": -9194.0, "z": 15826.4}, {"x": -9147.9, "z": 15743.8}, {"x": -9105.7, "z": 15668.2}, {"x": -9083.3, "z": 15629.1}, {"x": -9054.8, "z": 15580.8}, {"x": -9050.6, "z": 15573.9}, {"x": -9043.9, "z": 15564.1}, {"x": -9038.7, "z": 15557.5}, {"x": -9034.7, "z": 15553.2}, {"x": -9027.3, "z": 15546.1}, {"x": -9021.1, "z": 15541.2}, {"x": -9018.4, "z": 15539.7}, {"x": -9014.5, "z": 15537.5}, {"x": -9008.1, "z": 15535.2}, {"x": -9003.7, "z": 15534.1}, {"x": -9000.8, "z": 15533.4}, {"x": -8984.8, "z": 15531.8}, {"x": -8924.1, "z": 15528.3}, {"x": -8888.4, "z": 15526.2}, {"x": -8848.9, "z": 15525.3}, {"x": -8829.0, "z": 15525.6}, {"x": -8804.9, "z": 15526.3}, {"x": -8789.1, "z": 15526.8}, {"x": -8762.9, "z": 15527.9}, {"x": -8749.0, "z": 15528.5}, {"x": -8589.9, "z": 15533.3}, {"x": -8510.5, "z": 15535.2}, {"x": -8490.4, "z": 15536.0}, {"x": -8295.6, "z": 15540.6}, {"x": -8285.5, "z": 15540.8}, {"x": -8272.3, "z": 15541.1}, {"x": -8265.4, "z": 15541.3}, {"x": -8247.0, "z": 15540.6}, {"x": -8237.0, "z": 15540.3}, {"x": -8126.8, "z": 15534.4}, {"x": -8095.4, "z": 15532.3}, {"x": -8091.8, "z": 15531.7}, {"x": -8089.3, "z": 15531.3}, {"x": -8084.9, "z": 15530.2}, {"x": -8077.0, "z": 15527.3}, {"x": -8069.7, "z": 15523.2}, {"x": -8064.2, "z": 15519.3}, {"x": -8056.9, "z": 15512.6}, {"x": -8052.8, "z": 15508.2}, {"x": -8043.9, "z": 15496.8}, {"x": -8037.8, "z": 15487.1}, {"x": -8035.5, "z": 15482.8}, {"x": -8030.0, "z": 15470.8}, {"x": -8027.1, "z": 15463.7}, {"x": -8022.4, "z": 15450.1}, {"x": -8014.0, "z": 15423.2}, {"x": -7989.8, "z": 15347.9}, {"x": -7983.1, "z": 15329.7}, {"x": -7980.5, "z": 15323.6}, {"x": -7975.9, "z": 15314.6}, {"x": -7971.3, "z": 15306.6}, {"x": -7965.8, "z": 15298.7}, {"x": -7958.4, "z": 15290.0}, {"x": -7950.5, "z": 15282.0}, {"x": -7943.0, "z": 15275.9}, {"x": -7935.5, "z": 15271.2}, {"x": -7928.8, "z": 15268.3}, {"x": -7923.4, "z": 15266.6}, {"x": -7914.6, "z": 15265.1}, {"x": -7907.3, "z": 15264.5}, {"x": -7838.6, "z": 15261.9}, {"x": -7824.8, "z": 15261.2}, {"x": -7822.1, "z": 15261.0}, {"x": -7815.8, "z": 15260.7}, {"x": -7800.5, "z": 15259.7}, {"x": -7795.9, "z": 15259.4}, {"x": -7793.6, "z": 15259.3}, {"x": -7742.4, "z": 15256.0}, {"x": -7730.1, "z": 15255.6}, {"x": -7727.8, "z": 15255.6}, {"x": -7708.3, "z": 15254.6}, {"x": -7702.0, "z": 15254.5}, {"x": -7675.4, "z": 15253.6}, {"x": -7671.0, "z": 15253.8}, {"x": -7660.9, "z": 15254.2}, {"x": -7577.4, "z": 15262.2}, {"x": -7565.0, "z": 15263.4}, {"x": -7511.5, "z": 15268.5}, {"x": -7477.9, "z": 15272.0}, {"x": -7470.4, "z": 15272.8}, {"x": -7463.4, "z": 15273.4}, {"x": -7449.7, "z": 15274.6}, {"x": -7419.3, "z": 15277.7}, {"x": -7414.7, "z": 15277.8}, {"x": -7412.2, "z": 15277.9}, {"x": -7403.6, "z": 15277.7}, {"x": -7394.2, "z": 15275.8}, {"x": -7390.0, "z": 15274.2}, {"x": -7384.7, "z": 15271.7}, {"x": -7381.2, "z": 15269.8}, {"x": -7374.7, "z": 15265.3}, {"x": -7367.7, "z": 15258.9}, {"x": -7361.2, "z": 15251.6}, {"x": -7336.8, "z": 15220.2}, {"x": -7313.9, "z": 15190.9}, {"x": -7293.4, "z": 15163.9}, {"x": -7279.4, "z": 15146.1}, {"x": -7234.2, "z": 15088.1}, {"x": -7217.3, "z": 15065.8}, {"x": -7144.4, "z": 14971.6}, {"x": -7103.9, "z": 14918.9}, {"x": -7100.6, "z": 14912.8}, {"x": -7099.3, "z": 14909.4}, {"x": -7097.8, "z": 14905.0}], "type": "tertiary", "name": "County Road D"}, {"coords": [{"x": -9455.6, "z": 14625.9}, {"x": -9456.9, "z": 14622.9}, {"x": -9457.4, "z": 14619.7}, {"x": -9458.2, "z": 14617.7}, {"x": -9458.4, "z": 14613.8}, {"x": -9458.7, "z": 14582.0}, {"x": -9459.3, "z": 14529.2}, {"x": -9459.8, "z": 14424.9}, {"x": -9460.0, "z": 14412.8}, {"x": -9460.0, "z": 14407.5}], "type": "service", "name": "Slinger Road"}, {"coords": [{"x": -9018.4, "z": 15539.7}, {"x": -9018.4, "z": 15533.6}, {"x": -9018.3, "z": 15530.0}, {"x": -9017.6, "z": 15521.5}, {"x": -9016.6, "z": 15508.7}, {"x": -9016.4, "z": 15499.3}, {"x": -9016.2, "z": 15491.0}, {"x": -9015.9, "z": 15462.6}, {"x": -9015.3, "z": 15370.5}, {"x": -9015.3, "z": 15292.6}, {"x": -9015.0, "z": 15217.9}, {"x": -9015.0, "z": 15139.3}, {"x": -9014.5, "z": 15062.8}, {"x": -9014.5, "z": 14996.5}, {"x": -9013.9, "z": 14979.7}, {"x": -9013.3, "z": 14972.6}, {"x": -9012.6, "z": 14967.2}, {"x": -9011.6, "z": 14961.8}, {"x": -9010.5, "z": 14956.8}, {"x": -9009.0, "z": 14951.6}, {"x": -9007.1, "z": 14946.2}, {"x": -9002.4, "z": 14935.6}, {"x": -8999.0, "z": 14928.5}, {"x": -8990.8, "z": 14911.9}, {"x": -8918.4, "z": 14763.7}, {"x": -8900.7, "z": 14727.0}, {"x": -8882.3, "z": 14689.6}, {"x": -8865.2, "z": 14653.8}, {"x": -8847.1, "z": 14617.4}, {"x": -8828.8, "z": 14579.4}, {"x": -8809.8, "z": 14541.6}, {"x": -8795.0, "z": 14511.6}, {"x": -8793.1, "z": 14506.1}, {"x": -8792.6, "z": 14504.0}, {"x": -8792.3, "z": 14502.0}, {"x": -8792.2, "z": 14498.1}], "type": "residential", "name": "Owl Road"}, {"coords": [{"x": -10538.2, "z": 15979.5}, {"x": -10512.6, "z": 15943.0}, {"x": -10511.6, "z": 15941.5}, {"x": -10509.1, "z": 15937.9}, {"x": -10483.0, "z": 15900.6}, {"x": -10407.9, "z": 15793.4}, {"x": -10400.0, "z": 15782.8}, {"x": -10392.0, "z": 15772.5}, {"x": -10386.0, "z": 15765.2}, {"x": -10372.3, "z": 15750.3}, {"x": -10362.9, "z": 15740.2}, {"x": -10361.6, "z": 15738.7}, {"x": -10293.2, "z": 15667.0}, {"x": -10243.4, "z": 15614.1}, {"x": -10195.1, "z": 15563.3}, {"x": -10183.0, "z": 15549.7}, {"x": -10177.8, "z": 15543.9}, {"x": -10155.2, "z": 15516.9}, {"x": -10143.2, "z": 15502.5}, {"x": -10073.8, "z": 15417.4}, {"x": -10060.3, "z": 15401.1}, {"x": -10056.7, "z": 15396.7}, {"x": -10052.8, "z": 15391.8}, {"x": -10043.9, "z": 15380.8}, {"x": -10005.4, "z": 15333.7}, {"x": -9853.2, "z": 15150.6}, {"x": -9835.6, "z": 15129.0}, {"x": -9758.4, "z": 15036.0}, {"x": -9724.7, "z": 14995.2}, {"x": -9696.8, "z": 14961.9}, {"x": -9682.5, "z": 14944.3}, {"x": -9663.0, "z": 14921.0}, {"x": -9644.4, "z": 14898.2}, {"x": -9607.5, "z": 14853.8}, {"x": -9589.3, "z": 14831.6}, {"x": -9519.4, "z": 14747.6}, {"x": -9512.9, "z": 14738.7}, {"x": -9506.3, "z": 14728.3}, {"x": -9505.3, "z": 14726.4}, {"x": -9501.6, "z": 14719.5}, {"x": -9455.6, "z": 14625.9}, {"x": -9426.9, "z": 14566.9}, {"x": -9420.5, "z": 14554.3}, {"x": -9415.3, "z": 14545.7}, {"x": -9407.3, "z": 14534.4}, {"x": -9397.8, "z": 14524.0}, {"x": -9390.3, "z": 14517.1}, {"x": -9386.8, "z": 14514.3}, {"x": -9380.2, "z": 14509.7}, {"x": -9373.4, "z": 14505.8}, {"x": -9362.6, "z": 14501.8}, {"x": -9353.3, "z": 14500.2}, {"x": -9342.7, "z": 14499.7}, {"x": -9252.6, "z": 14498.3}, {"x": -9168.2, "z": 14497.6}, {"x": -9105.3, "z": 14497.0}, {"x": -9080.7, "z": 14496.4}, {"x": -9077.4, "z": 14496.4}, {"x": -9054.5, "z": 14496.3}, {"x": -8988.2, "z": 14495.6}, {"x": -8932.1, "z": 14495.0}, {"x": -8877.3, "z": 14496.0}, {"x": -8874.7, "z": 14496.0}, {"x": -8835.4, "z": 14496.8}, {"x": -8792.2, "z": 14498.1}, {"x": -8711.4, "z": 14500.0}, {"x": -8699.8, "z": 14499.9}, {"x": -8694.8, "z": 14499.3}, {"x": -8687.9, "z": 14497.8}, {"x": -8680.8, "z": 14494.9}, {"x": -8673.9, "z": 14490.7}, {"x": -8670.1, "z": 14488.1}, {"x": -8661.7, "z": 14480.4}, {"x": -8657.8, "z": 14476.4}, {"x": -8651.4, "z": 14469.0}, {"x": -8645.3, "z": 14460.3}, {"x": -8631.1, "z": 14436.7}, {"x": -8589.2, "z": 14363.2}, {"x": -8547.7, "z": 14291.6}, {"x": -8481.6, "z": 14176.1}, {"x": -8472.2, "z": 14162.2}, {"x": -8467.9, "z": 14156.7}, {"x": -8459.2, "z": 14146.8}, {"x": -8454.2, "z": 14142.1}, {"x": -8444.9, "z": 14134.2}, {"x": -8439.4, "z": 14130.5}, {"x": -8434.3, "z": 14127.5}, {"x": -8432.7, "z": 14126.7}, {"x": -8422.7, "z": 14121.7}, {"x": -8413.9, "z": 14118.6}, {"x": -8410.2, "z": 14117.7}, {"x": -8401.7, "z": 14116.7}, {"x": -8396.5, "z": 14116.5}, {"x": -8390.1, "z": 14116.6}, {"x": -8384.7, "z": 14117.1}, {"x": -8377.3, "z": 14118.6}, {"x": -8370.5, "z": 14120.6}, {"x": -8358.0, "z": 14126.0}, {"x": -8345.1, "z": 14132.7}, {"x": -8332.7, "z": 14139.8}, {"x": -8278.8, "z": 14168.6}, {"x": -8274.5, "z": 14170.9}, {"x": -8242.0, "z": 14188.7}, {"x": -8217.5, "z": 14201.6}, {"x": -8200.9, "z": 14210.3}, {"x": -8180.8, "z": 14220.9}, {"x": -8178.2, "z": 14222.1}, {"x": -8171.8, "z": 14225.2}, {"x": -8163.5, "z": 14228.8}, {"x": -8156.0, "z": 14231.7}, {"x": -8147.7, "z": 14234.6}, {"x": -8137.1, "z": 14237.5}, {"x": -8126.9, "z": 14239.8}, {"x": -8108.9, "z": 14242.4}, {"x": -8099.7, "z": 14243.0}, {"x": -8083.9, "z": 14242.6}, {"x": -8039.3, "z": 14239.1}, {"x": -7986.5, "z": 14234.4}, {"x": -7977.2, "z": 14232.7}, {"x": -7973.3, "z": 14231.5}, {"x": -7968.6, "z": 14229.1}, {"x": -7961.9, "z": 14225.7}, {"x": -7958.8, "z": 14223.1}, {"x": -7952.2, "z": 14216.7}, {"x": -7947.6, "z": 14210.9}, {"x": -7945.2, "z": 14207.9}, {"x": -7942.0, "z": 14203.2}, {"x": -7928.0, "z": 14181.1}], "type": "tertiary", "name": "County Road DE"}, {"coords": [{"x": -8127.7, "z": 15937.7}, {"x": -8127.3, "z": 15864.0}, {"x": -8127.3, "z": 15752.3}, {"x": -8127.4, "z": 15715.1}, {"x": -8127.3, "z": 15678.2}, {"x": -8127.2, "z": 15639.0}, {"x": -8127.2, "z": 15603.9}, {"x": -8126.8, "z": 15534.4}], "type": "service", "name": "Schaefer Road"}, {"coords": [{"x": -8416.9, "z": 14770.1}, {"x": -8415.6, "z": 14769.6}, {"x": -8412.3, "z": 14769.1}, {"x": -8353.8, "z": 14772.5}, {"x": -8332.2, "z": 14773.1}, {"x": -8274.9, "z": 14775.6}], "type": "residential", "name": "Callies Drive"}, {"coords": [{"x": -8775.9, "z": 13518.2}, {"x": -8822.6, "z": 13594.1}, {"x": -8845.4, "z": 13630.6}, {"x": -8890.3, "z": 13703.4}, {"x": -8959.9, "z": 13815.2}, {"x": -9008.4, "z": 13892.2}, {"x": -9024.4, "z": 13918.1}, {"x": -9031.0, "z": 13929.6}, {"x": -9051.9, "z": 13971.8}, {"x": -9055.2, "z": 13978.7}, {"x": -9073.4, "z": 14016.5}, {"x": -9090.5, "z": 14051.6}, {"x": -9123.5, "z": 14120.7}, {"x": -9140.4, "z": 14156.7}, {"x": -9158.5, "z": 14197.0}, {"x": -9165.0, "z": 14212.1}, {"x": -9166.8, "z": 14217.1}, {"x": -9168.2, "z": 14221.8}, {"x": -9169.2, "z": 14226.8}, {"x": -9169.8, "z": 14232.2}, {"x": -9170.2, "z": 14239.3}, {"x": -9170.3, "z": 14246.6}, {"x": -9170.3, "z": 14279.5}, {"x": -9168.2, "z": 14497.6}], "type": "residential", "name": "Hawk Road"}, {"coords": [{"x": -9232.6, "z": 15271.2}, {"x": -9271.9, "z": 15272.9}, {"x": -9289.5, "z": 15274.6}, {"x": -9309.1, "z": 15279.7}, {"x": -9315.0, "z": 15278.1}, {"x": -9319.4, "z": 15275.8}, {"x": -9322.8, "z": 15269.5}, {"x": -9339.3, "z": 15225.9}, {"x": -9350.8, "z": 15199.5}], "type": "service", "name": ""}, {"coords": [{"x": -8924.1, "z": 15528.3}, {"x": -8924.0, "z": 15534.5}, {"x": -8923.4, "z": 15537.9}, {"x": -8922.0, "z": 15540.5}, {"x": -8919.9, "z": 15542.9}, {"x": -8917.0, "z": 15543.9}, {"x": -8912.8, "z": 15544.6}, {"x": -8909.6, "z": 15546.3}, {"x": -8906.1, "z": 15549.7}, {"x": -8900.6, "z": 15557.6}, {"x": -8893.5, "z": 15566.7}, {"x": -8889.2, "z": 15572.9}, {"x": -8887.0, "z": 15577.6}, {"x": -8885.8, "z": 15584.0}], "type": "service", "name": ""}, {"coords": [{"x": -9750.5, "z": 15368.5}, {"x": -9771.4, "z": 15404.7}, {"x": -9786.3, "z": 15431.1}, {"x": -9801.6, "z": 15458.9}, {"x": -9822.4, "z": 15498.5}], "type": "service", "name": ""}, {"coords": [{"x": -9629.4, "z": 15987.3}, {"x": -9637.1, "z": 15968.4}, {"x": -9642.0, "z": 15954.9}, {"x": -9647.6, "z": 15936.8}, {"x": -9654.3, "z": 15930.5}, {"x": -9659.5, "z": 15933.7}, {"x": -9663.5, "z": 15944.0}, {"x": -9668.1, "z": 15944.2}, {"x": -9674.0, "z": 15943.4}, {"x": -9680.9, "z": 15942.5}, {"x": -9684.9, "z": 15941.3}, {"x": -9693.7, "z": 15941.2}, {"x": -9699.8, "z": 15939.0}, {"x": -9720.9, "z": 15934.8}, {"x": -9731.3, "z": 15930.7}, {"x": -9736.1, "z": 15930.1}, {"x": -9739.5, "z": 15930.9}, {"x": -9742.4, "z": 15936.3}, {"x": -9745.3, "z": 15946.5}, {"x": -9747.7, "z": 15958.1}, {"x": -9757.0, "z": 15998.6}], "type": "service", "name": ""}, {"coords": [{"x": -9714.8, "z": 15416.6}, {"x": -9712.9, "z": 15405.8}, {"x": -9710.3, "z": 15394.5}, {"x": -9708.7, "z": 15386.9}, {"x": -9706.0, "z": 15380.0}, {"x": -9702.0, "z": 15375.1}, {"x": -9698.3, "z": 15373.8}, {"x": -9693.3, "z": 15376.1}], "type": "service", "name": ""}, {"coords": [{"x": -8432.7, "z": 14126.7}, {"x": -8439.0, "z": 14103.5}, {"x": -8441.9, "z": 14097.4}, {"x": -8447.9, "z": 14090.5}, {"x": -8457.2, "z": 14083.3}, {"x": -8462.5, "z": 14085.8}, {"x": -8467.6, "z": 14085.5}, {"x": -8473.0, "z": 14080.2}, {"x": -8478.0, "z": 14074.8}, {"x": -8483.2, "z": 14071.1}, {"x": -8487.7, "z": 14068.3}, {"x": -8491.7, "z": 14066.1}, {"x": -8499.4, "z": 14061.8}, {"x": -8507.1, "z": 14057.1}, {"x": -8514.7, "z": 14052.5}, {"x": -8526.4, "z": 14044.6}], "type": "service", "name": ""}, {"coords": [{"x": -9016.4, "z": 15499.3}, {"x": -9024.2, "z": 15498.7}, {"x": -9029.3, "z": 15498.4}, {"x": -9032.0, "z": 15499.3}, {"x": -9034.2, "z": 15501.6}, {"x": -9035.6, "z": 15505.3}, {"x": -9035.2, "z": 15509.5}, {"x": -9034.3, "z": 15513.6}, {"x": -9031.6, "z": 15517.1}, {"x": -9028.9, "z": 15518.6}, {"x": -9023.3, "z": 15520.5}, {"x": -9017.6, "z": 15521.5}], "type": "service", "name": ""}, {"coords": [{"x": -8295.6, "z": 15540.6}, {"x": -8297.0, "z": 15554.3}, {"x": -8299.9, "z": 15575.4}, {"x": -8302.8, "z": 15606.2}, {"x": -8304.7, "z": 15624.9}, {"x": -8305.8, "z": 15638.7}, {"x": -8307.0, "z": 15644.7}, {"x": -8312.8, "z": 15659.2}], "type": "service", "name": ""}, {"coords": [{"x": -8200.9, "z": 14210.3}, {"x": -8198.4, "z": 14180.7}, {"x": -8196.6, "z": 14163.4}], "type": "service", "name": ""}, {"coords": [{"x": -9137.4, "z": 15008.9}, {"x": -9131.6, "z": 15006.9}, {"x": -9127.2, "z": 15005.5}, {"x": -9122.9, "z": 15004.0}, {"x": -9118.5, "z": 15002.7}, {"x": -9113.8, "z": 15001.1}, {"x": -9106.7, "z": 14999.7}, {"x": -9097.1, "z": 14998.6}, {"x": -9089.9, "z": 14998.3}, {"x": -9086.6, "z": 14997.6}, {"x": -9084.3, "z": 14997.1}, {"x": -9082.2, "z": 14996.8}], "type": "service", "name": ""}, {"coords": [{"x": -8217.5, "z": 14201.6}, {"x": -8219.8, "z": 14162.2}], "type": "service", "name": ""}, {"coords": [{"x": -8275.3, "z": 14593.3}, {"x": -8278.7, "z": 14593.3}, {"x": -8282.4, "z": 14592.0}, {"x": -8291.8, "z": 14588.6}, {"x": -8295.4, "z": 14586.8}, {"x": -8297.8, "z": 14580.0}], "type": "service", "name": ""}, {"coords": [{"x": -8137.1, "z": 14237.5}, {"x": -8138.3, "z": 14246.6}, {"x": -8139.4, "z": 14255.9}, {"x": -8140.9, "z": 14267.1}, {"x": -8141.8, "z": 14272.0}, {"x": -8142.9, "z": 14275.5}, {"x": -8144.6, "z": 14281.6}], "type": "service", "name": ""}, {"coords": [{"x": -8178.2, "z": 14222.1}, {"x": -8178.7, "z": 14229.5}, {"x": -8178.8, "z": 14236.8}, {"x": -8178.1, "z": 14244.6}, {"x": -8177.3, "z": 14253.6}], "type": "service", "name": ""}, {"coords": [{"x": -9015.9, "z": 15462.6}, {"x": -9011.1, "z": 15461.0}, {"x": -9007.4, "z": 15458.3}, {"x": -9003.7, "z": 15449.5}, {"x": -8999.7, "z": 15438.5}, {"x": -8995.5, "z": 15426.8}, {"x": -8992.7, "z": 15420.4}], "type": "service", "name": ""}, {"coords": [{"x": -8272.5, "z": 15503.9}, {"x": -8256.1, "z": 15502.2}, {"x": -8253.8, "z": 15503.5}, {"x": -8253.2, "z": 15510.5}, {"x": -8251.4, "z": 15515.7}, {"x": -8247.2, "z": 15522.5}, {"x": -8247.0, "z": 15540.6}], "type": "service", "name": ""}, {"coords": [{"x": -8285.5, "z": 15540.8}, {"x": -8285.7, "z": 15520.8}], "type": "service", "name": ""}, {"coords": [{"x": -8988.2, "z": 14495.6}, {"x": -8987.1, "z": 14471.1}, {"x": -8985.9, "z": 14456.4}], "type": "service", "name": ""}, {"coords": [{"x": -9147.9, "z": 15743.8}, {"x": -9142.5, "z": 15756.2}, {"x": -9139.3, "z": 15764.1}, {"x": -9137.6, "z": 15771.2}, {"x": -9136.9, "z": 15776.3}], "type": "service", "name": ""}]